maads/__init__.py
maads/balancedata.py
maads/callmas.py
maads/sendfiles.py
maads-5.2.3.dist-info/METADATA
maads-5.2.3.dist-info/WHEEL
maads-5.2.3.dist-info/license.txt
maads-5.2.3.dist-info/top_level.txt
maads-5.2.3.dist-info/RECORD
